segpy/__init__.py
segpy/__main__.py
segpy/binary_reel_header.py
segpy/catalog.py
segpy/cli.py
segpy/dataset.py
segpy/datatypes.py
segpy/encoding.py
segpy/field_types.py
segpy/header.py
segpy/ibm_float.py
segpy/ibm_float_packer.py
segpy/packer.py
segpy/reader.py
segpy/reversed_sequence_view.py
segpy/revisions.py
segpy/sorted_frozen_set.py
segpy/textual_reel_header.py
segpy/toolkit.py
segpy/trace_header.py
segpy/util.py
segpy/writer.py
segpy-2.1.0.dist-info/LICENSE
segpy-2.1.0.dist-info/METADATA
segpy-2.1.0.dist-info/WHEEL
segpy-2.1.0.dist-info/entry_points.txt
segpy-2.1.0.dist-info/top_level.txt
segpy-2.1.0.dist-info/RECORD
