Metadata-Version: 2.1
Name: segpy
Version: 2.1.0
Summary: Transfer of seismic data to and from SEG Y files
Home-page: https://github.com/sixty-north/segpy
Author: Sixty North AS
Author-email: rob@sixty-north.com
License: GNU Affero General Public License v3
Keywords: seismic geocomputing geophysics
Platform: UNKNOWN
Classifier: Development Status :: 5 - Production/Stable
Classifier: Intended Audience :: Developers
Classifier: Topic :: Scientific/Engineering
Classifier: Topic :: Software Development :: Libraries
Classifier: License :: OSI Approved :: GNU Affero General Public License v3
Classifier: Programming Language :: Python :: 3 :: Only
Provides-Extra: dev
Provides-Extra: doc
Provides-Extra: test
